odoo/addons/shopinvader_anonymous_partner/README.rst
odoo/addons/shopinvader_anonymous_partner/__init__.py
odoo/addons/shopinvader_anonymous_partner/__manifest__.py
odoo/addons/shopinvader_anonymous_partner/i18n/shopinvader_anonymous_partner.pot
odoo/addons/shopinvader_anonymous_partner/models/__init__.py
odoo/addons/shopinvader_anonymous_partner/models/cookie_helper.py
odoo/addons/shopinvader_anonymous_partner/models/res_partner.py
odoo/addons/shopinvader_anonymous_partner/readme/DESCRIPTION.rst
odoo/addons/shopinvader_anonymous_partner/readme/ROADMAP.rst
odoo/addons/shopinvader_anonymous_partner/readme/USAGE.rst
odoo/addons/shopinvader_anonymous_partner/static/description/index.html
odoo/addons/shopinvader_anonymous_partner/tests/__init__.py
odoo/addons/shopinvader_anonymous_partner/tests/test_anonymous_partner.py
odoo_addon_shopinvader_anonymous_partner-16.0.1.1.2.dist-info/METADATA
odoo_addon_shopinvader_anonymous_partner-16.0.1.1.2.dist-info/WHEEL
odoo_addon_shopinvader_anonymous_partner-16.0.1.1.2.dist-info/top_level.txt
odoo_addon_shopinvader_anonymous_partner-16.0.1.1.2.dist-info/RECORD
